aws_clipper/__init__.py
aws_clipper/__main__.py
aws_clipper/cli.py
aws_clipper-0.1.3.dist-info/LICENSE
aws_clipper-0.1.3.dist-info/METADATA
aws_clipper-0.1.3.dist-info/WHEEL
aws_clipper-0.1.3.dist-info/entry_points.txt
aws_clipper-0.1.3.dist-info/RECORD
