Metadata-Version: 2.1
Name: aws-clipper
Version: 0.1.3
Summary: `aws-clipper` dumps AWS CLI config from a simple YAML file.
Home-page: https://github.com/kai2nenobu/aws-clipper
License: MIT
Keywords: aws
Author: kai2nenobu
Author-email: kai2nenobu@gmail.com
Requires-Python: >=3.8.1
Classifier: Development Status :: 3 - Alpha
Classifier: Intended Audience :: Developers
Classifier: License :: OSI Approved :: MIT License
Classifier: Programming Language :: Python :: 3
Classifier: Programming Language :: Python :: 3.9
Classifier: Programming Language :: Python :: 3.10
Classifier: Programming Language :: Python :: 3.11
Classifier: Programming Language :: Python :: 3.12
Classifier: Programming Language :: Python :: 3.8
Requires-Dist: pyyaml (>=6.0,<7.0)
Project-URL: Bug Tracker, https://github.com/kai2nenobu/aws-clipper/issues
Project-URL: Changelog, https://github.com/kai2nenobu/aws-clipper/blob/main/CHANGELOG.md
Project-URL: Repository, https://github.com/kai2nenobu/aws-clipper
